odoo/addons/l10n_ro_stock_account/README.rst
odoo/addons/l10n_ro_stock_account/__init__.py
odoo/addons/l10n_ro_stock_account/__manifest__.py
odoo/addons/l10n_ro_stock_account/i18n/l10n_ro_stock_account.pot
odoo/addons/l10n_ro_stock_account/i18n/ro.po
odoo/addons/l10n_ro_stock_account/models/__init__.py
odoo/addons/l10n_ro_stock_account/models/account_account.py
odoo/addons/l10n_ro_stock_account/models/account_move.py
odoo/addons/l10n_ro_stock_account/models/account_move_line.py
odoo/addons/l10n_ro_stock_account/models/product_category.py
odoo/addons/l10n_ro_stock_account/models/product_template.py
odoo/addons/l10n_ro_stock_account/models/stock_location.py
odoo/addons/l10n_ro_stock_account/models/stock_move.py
odoo/addons/l10n_ro_stock_account/models/stock_picking.py
odoo/addons/l10n_ro_stock_account/models/stock_warehouse.py
odoo/addons/l10n_ro_stock_account/models/fifo/__init__.py
odoo/addons/l10n_ro_stock_account/models/fifo/product.py
odoo/addons/l10n_ro_stock_account/models/fifo/stock_lot.py
odoo/addons/l10n_ro_stock_account/models/fifo/stock_move.py
odoo/addons/l10n_ro_stock_account/models/fifo/stock_quant.py
odoo/addons/l10n_ro_stock_account/readme/CONTRIBUTORS.md
odoo/addons/l10n_ro_stock_account/readme/DESCRIPTION.md
odoo/addons/l10n_ro_stock_account/static/description/icon.png
odoo/addons/l10n_ro_stock_account/static/description/index.html
odoo/addons/l10n_ro_stock_account/tests/__init__.py
odoo/addons/l10n_ro_stock_account/tests/common.py
odoo/addons/l10n_ro_stock_account/tests/test_ro_stock_avg.py
odoo/addons/l10n_ro_stock_account/tests/test_ro_stock_fifo.py
odoo/addons/l10n_ro_stock_account/tests/test_stock_fifo_internal_transfer.py
odoo/addons/l10n_ro_stock_account/tests/test_stock_location.py
odoo/addons/l10n_ro_stock_account/tests/cases/test_cases_avg.csv
odoo/addons/l10n_ro_stock_account/tests/cases/test_cases_fifo.csv
odoo/addons/l10n_ro_stock_account/tests/cases/test_cases_fifo_transfer.csv
odoo_addon_l10n_ro_stock_account-19.0.0.10.0.1.dist-info/METADATA
odoo_addon_l10n_ro_stock_account-19.0.0.10.0.1.dist-info/WHEEL
odoo_addon_l10n_ro_stock_account-19.0.0.10.0.1.dist-info/top_level.txt
odoo_addon_l10n_ro_stock_account-19.0.0.10.0.1.dist-info/RECORD
